langium_runner/__init__.py
langium_runner/evaluator_runner.py
langium_runner/dist/bundle.cjs
langium_runner/generated/__init__.py
langium_runner/generated/langium_ai_tools/__init__.py
scripts/build.py
langium_runner-1.0.1.dist-info/METADATA
langium_runner-1.0.1.dist-info/WHEEL
langium_runner-1.0.1.dist-info/entry_points.txt
langium_runner-1.0.1.dist-info/top_level.txt
langium_runner-1.0.1.dist-info/RECORD
