Metadata-Version: 2.4
Name: langium_runner
Version: 1.0.1
Summary: A runner for evaluating Langium responses.
Home-page: https://github.com/TypeFox/langium-ai
Author: Typefox
Author-email: TypeFox <dennis.huebner@gmail.com>
Project-URL: Homepage, https://github.com/TypeFox/langium-ai
Project-URL: Repository, https://github.com/TypeFox/langium-ai
Classifier: Programming Language :: Python :: 3
Classifier: Programming Language :: Python :: 3.8
Classifier: Programming Language :: Python :: 3.9
Classifier: Programming Language :: Python :: 3.10
Classifier: Programming Language :: Python :: 3.11
Classifier: Programming Language :: Python :: 3.12
Classifier: License :: OSI Approved :: MIT License
Classifier: Operating System :: OS Independent
Requires-Python: >=3.9
Requires-Dist: betterproto>=2.0.0b3
Provides-Extra: build
Requires-Dist: betterproto[compiler]>=2.0.0b3; extra == "build"
Requires-Dist: grpcio-tools>=1.60.0; extra == "build"
Provides-Extra: dist
Requires-Dist: build>=1.0.0; extra == "dist"
Requires-Dist: twine>=4.0.0; extra == "dist"
Requires-Dist: wheel>=0.40.0; extra == "dist"
Provides-Extra: test
Requires-Dist: pytest>=7.0.0; extra == "test"
Requires-Dist: pytest-cov>=4.0.0; extra == "test"
Provides-Extra: lint
Requires-Dist: black>=23.1.0; extra == "lint"
Requires-Dist: isort>=5.11.5; extra == "lint"
Requires-Dist: mypy>=1.0.0; extra == "lint"
Provides-Extra: dev
Requires-Dist: betterproto[compiler]>=2.0.0b3; extra == "dev"
Requires-Dist: grpcio-tools>=1.60.0; extra == "dev"
Requires-Dist: pytest>=7.0.0; extra == "dev"
Requires-Dist: pytest-cov>=4.0.0; extra == "dev"
Requires-Dist: black>=23.1.0; extra == "dev"
Requires-Dist: isort>=5.11.5; extra == "dev"
Requires-Dist: mypy>=1.0.0; extra == "dev"
Requires-Dist: build>=1.0.0; extra == "dev"
Requires-Dist: twine>=4.0.0; extra == "dev"
Requires-Dist: wheel>=0.40.0; extra == "dev"
Dynamic: author
Dynamic: home-page
Dynamic: requires-python
